Ascopy/Ascopy.py
Ascopy/__init__.py
Ascopy/copula.py
Ascopy/stats_func.py
Ascopy-0.0.1.dist-info/LICENSE.txt
Ascopy-0.0.1.dist-info/METADATA
Ascopy-0.0.1.dist-info/WHEEL
Ascopy-0.0.1.dist-info/top_level.txt
Ascopy-0.0.1.dist-info/RECORD
